README.txt
setup.cfg
setup.py
docs/HISTORY.txt
extdirect/README.txt
extdirect/__init__.py
extdirect/router.py
extdirect/tests.py
extdirect.egg-info/PKG-INFO
extdirect.egg-info/SOURCES.txt
extdirect.egg-info/dependency_links.txt
extdirect.egg-info/entry_points.txt
extdirect.egg-info/namespace_packages.txt
extdirect.egg-info/not-zip-safe
extdirect.egg-info/requires.txt
extdirect.egg-info/top_level.txt
extdirect/django/README.txt
extdirect/django/__init__.py
extdirect/django/registry.py
extdirect/django/router.py
extdirect/django/urls.py
extdirect/django/templatetags/__init__.py
extdirect/django/templatetags/direct_providers.py
extdirect/zope/README.txt
extdirect/zope/__init__.py
extdirect/zope/configure.zcml
extdirect/zope/interfaces.py
extdirect/zope/javascript.py
extdirect/zope/meta.zcml
extdirect/zope/metaconfigure.py
extdirect/zope/metadirectives.py
extdirect/zope/router.py