Metadata-Version: 1.0
Name: extdirect
Version: 0.4
Summary: Python implementation of an Ext.Direct router
Home-page: http://code.google.com/p/extdirect
Author: Ian McCracken
Author-email: ian@zenoss.com
License: BSD
Platform: UNKNOWN
Classifier: Programming Language :: Python
Classifier: Topic :: Software Development :: Libraries :: Python Modules
